[
    {
      "id": 1,
      "name": "John Doe",
      "age": 25,
      "gender": "male",
      "villageId": 1
    },
    {
      "id": 2,
      "name": "Jane Smith",
      "age": 30,
      "gender": "female",
      "villageId": 1
    },
    {
      "id": 3,
      "name": "Michael Brown",
      "age": 22,
      "gender": "male",
      "villageId": 1
    },
    {
      "id": 4,
      "name": "Sarah Johnson",
      "age": 28,
      "gender": "female",
      "villageId": 2
    },
    {
      "id": 5,
      "name": "Emily Davis",
      "age": 35,
      "gender": "female",
      "villageId": 2
    },
    {
      "id": 6,
      "name": "David Wilson",
      "age": 40,
      "gender": "male",
      "villageId": 2
    },
    {
      "id": 7,
      "name": "Chris Evans",
      "age": 19,
      "gender": "male",
      "villageId": 3
    },
    {
      "id": 8,
      "name": "Jessica Lee",
      "age": 23,
      "gender": "female",
      "villageId": 3
    },
    {
      "id": 9,
      "name": "Daniel Taylor",
      "age": 31,
      "gender": "male",
      "villageId": 3
    },
    {
      "id": 10,
      "name": "Sophia Martinez",
      "age": 27,
      "gender": "female",
      "villageId": 4
    },
    {
      "id": 11,
      "name": "Olivia Anderson",
      "age": 29,
      "gender": "female",
      "villageId": 4
    },
    {
      "id": 12,
      "name": "Jacob Thomas",
      "age": 33,
      "gender": "male",
      "villageId": 4
    },
    {
      "id": 13,
      "name": "Mia Hernandez",
      "age": 21,
      "gender": "female",
      "villageId": 5
    },
    {
      "id": 14,
      "name": "William Moore",
      "age": 26,
      "gender": "male",
      "villageId": 5
    },
    {
      "id": 15,
      "name": "James Harris",
      "age": 38,
      "gender": "male",
      "villageId": 5
    },
    {
      "id": 16,
      "name": "Ethan Clark",
      "age": 24,
      "gender": "male",
      "villageId": 6
    },
    {
      "id": 17,
      "name": "Ava Lewis",
      "age": 30,
      "gender": "female",
      "villageId": 6
    },
    {
      "id": 18,
      "name": "Isabella Young",
      "age": 32,
      "gender": "female",
      "villageId": 6
    },
    {
      "id": 19,
      "name": "Liam Hall",
      "age": 27,
      "gender": "male",
      "villageId": 6
    }
  ]
  